{"items":[{"player_id":487,"name":"Nicolas Pepe","position":"FWD","club":"Villarreal CF","market_value_eur":6000000,"caps":57,"international_goals":12,"date_of_birth":"1995-05-29","height_cm":183,"team":{"kind":"team","team_id":19,"name":"Côte d'Ivoire","fifa_code":"CIV"}},{"player_id":350,"name":"Orlando Daniel Gill","position":"GK","club":"CA San Lorenzo","market_value_eur":6000000,"caps":7,"international_goals":0,"date_of_birth":"2000-06-11","height_cm":190,"team":{"kind":"team","team_id":14,"name":"Paraguay","fifa_code":"PAR"}},{"player_id":509,"name":"Pedro Jeampierre Vite","position":"MID","club":"Pumas UNAM","market_value_eur":6000000,"caps":18,"international_goals":1,"date_of_birth":"2002-03-09","height_cm":172,"team":{"kind":"team","team_id":20,"name":"Ecuador","fifa_code":"ECU"}},{"player_id":633,"name":"Romelu Lukaku","position":"FWD","club":"SSC Napoli","market_value_eur":6000000,"caps":127,"international_goals":90,"date_of_birth":"1993-05-13","height_cm":190,"team":{"kind":"team","team_id":25,"name":"Belgium","fifa_code":"BEL"}},{"player_id":1042,"name":"SEMEDONélson Nelson","position":"DEF","club":"Fenerbahçe SK","market_value_eur":6000000,"caps":51,"international_goals":0,"date_of_birth":"1993-11-16","height_cm":179,"team":{"kind":"team","team_id":41,"name":"Portugal","fifa_code":"POR"}},{"player_id":868,"name":"Sadio Mane","position":"FWD","club":"Al Nassr FC","market_value_eur":6000000,"caps":131,"international_goals":54,"date_of_birth":"1992-04-10","height_cm":175,"team":{"kind":"team","team_id":34,"name":"Senegal","fifa_code":"SEN"}},{"player_id":243,"name":"Soufiane Rahimi","position":"FWD","club":"Al Ain FC","market_value_eur":6000000,"caps":38,"international_goals":12,"date_of_birth":"1996-06-02","height_cm":180,"team":{"kind":"team","team_id":10,"name":"Morocco","fifa_code":"MAR"}},{"player_id":993,"name":"Stefan Posch","position":"DEF","club":"1. FSV Mainz 05","market_value_eur":6000000,"caps":53,"international_goals":5,"date_of_birth":"1997-05-14","height_cm":188,"team":{"kind":"team","team_id":39,"name":"Austria","fifa_code":"AUT"}},{"player_id":111,"name":"Stephen Eustaquio","position":"MID","club":"LAFC","market_value_eur":6000000,"caps":57,"international_goals":4,"date_of_birth":"1996-12-21","height_cm":175,"team":{"kind":"team","team_id":5,"name":"Canada","fifa_code":"CAN"}},{"player_id":463,"name":"Tahith Jose Girigorio Djorkaef Chong","position":"MID","club":"Shefield United FC","market_value_eur":6000000,"caps":7,"international_goals":3,"date_of_birth":"1999-12-04","height_cm":185,"team":{"kind":"team","team_id":18,"name":"Curaçao","fifa_code":"CUW"}},{"player_id":8,"name":"Álvaro Fidalgo","position":"MID","club":"Real Betis","market_value_eur":6000000,"caps":5,"international_goals":0,"date_of_birth":"1997-04-09","height_cm":175,"team":{"kind":"team","team_id":1,"name":"Mexico","fifa_code":"MEX"}},{"player_id":1139,"name":"Jaminton Leandro Campaz","position":"FWD","club":"CA Rosario Central","market_value_eur":5500000,"caps":11,"international_goals":2,"date_of_birth":"2000-05-24","height_cm":166,"team":{"kind":"team","team_id":44,"name":"Colombia","fifa_code":"COL"}},{"player_id":1136,"name":"Willer Emilio Ditta","position":"DEF","club":"CF Cruz Azul","market_value_eur":5500000,"caps":5,"international_goals":0,"date_of_birth":"1998-01-23","height_cm":179,"team":{"kind":"team","team_id":44,"name":"Colombia","fifa_code":"COL"}},{"player_id":548,"name":"Yukinari Sugawara","position":"DEF","club":"SV Werder Bremen","market_value_eur":5500000,"caps":23,"international_goals":2,"date_of_birth":"2000-06-28","height_cm":179,"team":{"kind":"team","team_id":22,"name":"Japan","fifa_code":"JPN"}},{"player_id":402,"name":"Altay Bayindir","position":"GK","club":"Manchester United FC","market_value_eur":5000000,"caps":12,"international_goals":0,"date_of_birth":"1998-04-14","height_cm":198,"team":{"kind":"team","team_id":16,"name":"Türkiye","fifa_code":"TUR"}},{"player_id":1070,"name":"Axel Tuanzebe","position":"DEF","club":"Burnley FC","market_value_eur":5000000,"caps":14,"international_goals":1,"date_of_birth":"1997-11-14","height_cm":188,"team":{"kind":"team","team_id":42,"name":"Congo DR","fifa_code":"COD"}},{"player_id":566,"name":"Ayumu Seko","position":"DEF","club":"Le Havre AC","market_value_eur":5000000,"caps":14,"international_goals":0,"date_of_birth":"2000-06-07","height_cm":186,"team":{"kind":"team","team_id":22,"name":"Japan","fifa_code":"JPN"}},{"player_id":296,"name":"Che Sac Everton Fred Adams","position":"FWD","club":"Torino FC","market_value_eur":5000000,"caps":48,"international_goals":13,"date_of_birth":"1996-07-13","height_cm":175,"team":{"kind":"team","team_id":12,"name":"Scotland","fifa_code":"SCO"}},{"player_id":711,"name":"Christopher Grant Wood","position":"FWD","club":"Nottingham Forest FC","market_value_eur":5000000,"caps":91,"international_goals":45,"date_of_birth":"1991-12-07","height_cm":191,"team":{"kind":"team","team_id":28,"name":"New Zealand","fifa_code":"NZL"}},{"player_id":92,"name":"David Jurasek","position":"DEF","club":"SK Slavia Praha","market_value_eur":5000000,"caps":18,"international_goals":1,"date_of_birth":"2000-08-07","height_cm":183,"team":{"kind":"team","team_id":4,"name":"Czechia","fifa_code":"CZE"}},{"player_id":1007,"name":"Dejan Ljubicic","position":"MID","club":"FC Schalke 04","market_value_eur":5000000,"caps":9,"international_goals":1,"date_of_birth":"1997-10-08","height_cm":187,"team":{"kind":"team","team_id":39,"name":"Austria","fifa_code":"AUT"}},{"player_id":399,"name":"Deniz Daniel Gul","position":"FWD","club":"FC Porto","market_value_eur":5000000,"caps":9,"international_goals":2,"date_of_birth":"2004-07-02","height_cm":192,"team":{"kind":"team","team_id":16,"name":"Türkiye","fifa_code":"TUR"}},{"player_id":1193,"name":"Dominik Kotarski","position":"GK","club":"FC København","market_value_eur":5000000,"caps":4,"international_goals":0,"date_of_birth":"2000-02-10","height_cm":190,"team":{"kind":"team","team_id":46,"name":"Croatia","fifa_code":"CRO"}},{"player_id":596,"name":"Elliot Karl Stroud","position":"DEF","club":"Mjällby AIF","market_value_eur":5000000,"caps":2,"international_goals":0,"date_of_birth":"2002-06-22","height_cm":185,"team":{"kind":"team","team_id":23,"name":"Sweden","fifa_code":"SWE"}},{"player_id":615,"name":"Ellyes Joris Skhiri","position":"MID","club":"Eintracht Frankfurt","market_value_eur":5000000,"caps":84,"international_goals":4,"date_of_birth":"1995-05-10","height_cm":185,"team":{"kind":"team","team_id":24,"name":"Tunisia","fifa_code":"TUN"}},{"player_id":592,"name":"Eric Anders Smith","position":"DEF","club":"FC St. Pauli","market_value_eur":5000000,"caps":2,"international_goals":0,"date_of_birth":"1997-01-08","height_cm":192,"team":{"kind":"team","team_id":23,"name":"Sweden","fifa_code":"SWE"}},{"player_id":156,"name":"Ermin Mahmic","position":"MID","club":"FC Slovan Liberec","market_value_eur":5000000,"caps":2,"international_goals":0,"date_of_birth":"2005-03-14","height_cm":182,"team":{"kind":"team","team_id":6,"name":"Bosnia and Herzegovina","fifa_code":"BIH"}},{"player_id":403,"name":"Evren Eren Elmali","position":"DEF","club":"Galatasaray SK","market_value_eur":5000000,"caps":23,"international_goals":0,"date_of_birth":"2000-07-07","height_cm":181,"team":{"kind":"team","team_id":16,"name":"Türkiye","fifa_code":"TUR"}},{"player_id":817,"name":"Facundo Pellistri","position":"FWD","club":"Panathinaikos FC","market_value_eur":5000000,"caps":39,"international_goals":2,"date_of_birth":"2001-12-20","height_cm":174,"team":{"kind":"team","team_id":32,"name":"Uruguay","fifa_code":"URU"}},{"player_id":644,"name":"Hans Vanaken","position":"MID","club":"Club Brugge","market_value_eur":5000000,"caps":35,"international_goals":7,"date_of_birth":"1992-08-24","height_cm":195,"team":{"kind":"team","team_id":25,"name":"Belgium","fifa_code":"BEL"}},{"player_id":586,"name":"Hjalmar Ekdal","position":"DEF","club":"Burnley FC","market_value_eur":5000000,"caps":13,"international_goals":0,"date_of_birth":"1998-10-21","height_cm":187,"team":{"kind":"team","team_id":23,"name":"Sweden","fifa_code":"SWE"}},{"player_id":72,"name":"Hyunjun Yang","position":"MID","club":"Celtic FC","market_value_eur":5000000,"caps":9,"international_goals":0,"date_of_birth":"2002-05-25","height_cm":179,"team":{"kind":"team","team_id":3,"name":"South Korea","fifa_code":"KOR"}},{"player_id":609,"name":"Ismael Seifallah Gharbi","position":"MID","club":"FC Augsburg","market_value_eur":5000000,"caps":18,"international_goals":2,"date_of_birth":"2004-04-10","height_cm":180,"team":{"kind":"team","team_id":24,"name":"Tunisia","fifa_code":"TUN"}},{"player_id":1214,"name":"Jerome Opoku","position":"DEF","club":"Ba ş ak ş ehir FK","market_value_eur":5000000,"caps":12,"international_goals":1,"date_of_birth":"1998-10-14","height_cm":197,"team":{"kind":"team","team_id":47,"name":"Ghana","fifa_code":"GHA"}},{"player_id":1225,"name":"Jose Angel Cordoba","position":"DEF","club":"Norwich City FC","market_value_eur":5000000,"caps":33,"international_goals":1,"date_of_birth":"2001-06-03","height_cm":189,"team":{"kind":"team","team_id":48,"name":"Panama","fifa_code":"PAN"}},{"player_id":1133,"name":"Juan Camilo Portilla","position":"MID","club":"Athletico Paranaense","market_value_eur":5000000,"caps":10,"international_goals":0,"date_of_birth":"1998-09-12","height_cm":181,"team":{"kind":"team","team_id":44,"name":"Colombia","fifa_code":"COL"}},{"player_id":342,"name":"Juan Jose Caceres","position":"DEF","club":"FC Dynamo Moscow","market_value_eur":5000000,"caps":18,"international_goals":0,"date_of_birth":"2000-06-01","height_cm":187,"team":{"kind":"team","team_id":14,"name":"Paraguay","fifa_code":"PAR"}},{"player_id":1123,"name":"Kevin Duvan Castano","position":"MID","club":"CA River Plate","market_value_eur":5000000,"caps":26,"international_goals":0,"date_of_birth":"2000-09-29","height_cm":179,"team":{"kind":"team","team_id":44,"name":"Colombia","fifa_code":"COL"}},{"player_id":941,"name":"Leandro Daniel Paredes","position":"MID","club":"CA Boca Juniors","market_value_eur":5000000,"caps":77,"international_goals":5,"date_of_birth":"1994-06-29","height_cm":182,"team":{"kind":"team","team_id":37,"name":"Argentina","fifa_code":"ARG"}},{"player_id":760,"name":"Lenini Kevin Pina","position":"MID","club":"FC Krasnodar","market_value_eur":5000000,"caps":32,"international_goals":3,"date_of_birth":"1997-01-27","height_cm":177,"team":{"kind":"team","team_id":30,"name":"Cabo Verde","fifa_code":"CPV"}},{"player_id":330,"name":"Maximilian Michael Arfsten","position":"DEF","club":"Columbus Crew","market_value_eur":5000000,"caps":20,"international_goals":1,"date_of_birth":"2001-04-19","height_cm":185,"team":{"kind":"team","team_id":13,"name":"USA","fifa_code":"USA"}},{"player_id":184,"name":"Miro Max Maria Muheim","position":"DEF","club":"Hamburger SV","market_value_eur":5000000,"caps":11,"international_goals":0,"date_of_birth":"1998-03-24","height_cm":182,"team":{"kind":"team","team_id":8,"name":"Switzerland","fifa_code":"SUI"}},{"player_id":675,"name":"Mostafa Mohamed Zizo","position":"FWD","club":"Al Ahly FC","market_value_eur":5000000,"caps":65,"international_goals":5,"date_of_birth":"1996-01-10","height_cm":175,"team":{"kind":"team","team_id":26,"name":"Egypt","fifa_code":"EGY"}},{"player_id":482,"name":"Oumar Diakite","position":"FWD","club":"Cercle Brugge","market_value_eur":5000000,"caps":29,"international_goals":6,"date_of_birth":"2003-12-20","height_cm":182,"team":{"kind":"team","team_id":19,"name":"Côte d'Ivoire","fifa_code":"CIV"}},{"player_id":870,"name":"Pape Cherif Ndiaye","position":"FWD","club":"Samsunspor","market_value_eur":5000000,"caps":19,"international_goals":4,"date_of_birth":"1996-01-23","height_cm":190,"team":{"kind":"team","team_id":34,"name":"Senegal","fifa_code":"SEN"}},{"player_id":493,"name":"Parfait Guiagon","position":"MID","club":"Sporting Charleroi","market_value_eur":5000000,"caps":5,"international_goals":0,"date_of_birth":"2001-02-22","height_cm":165,"team":{"kind":"team","team_id":19,"name":"Côte d'Ivoire","fifa_code":"CIV"}},{"player_id":259,"name":"Redouane Halhal","position":"DEF","club":"KV Mechelen","market_value_eur":5000000,"caps":3,"international_goals":0,"date_of_birth":"2003-03-05","height_cm":189,"team":{"kind":"team","team_id":10,"name":"Morocco","fifa_code":"MAR"}},{"player_id":969,"name":"Riyad Karim Mahrez","position":"FWD","club":"Al Ahli FC","market_value_eur":5000000,"caps":117,"international_goals":38,"date_of_birth":"1991-02-21","height_cm":179,"team":{"kind":"team","team_id":38,"name":"Algeria","fifa_code":"ALG"}},{"player_id":624,"name":"Sebastian Tounekti","position":"MID","club":"Celtic FC","market_value_eur":5000000,"caps":13,"international_goals":1,"date_of_birth":"2002-07-13","height_cm":182,"team":{"kind":"team","team_id":24,"name":"Tunisia","fifa_code":"TUN"}},{"player_id":568,"name":"Takehiro Tomiyasu","position":"DEF","club":"AFC Ajax","market_value_eur":5000000,"caps":44,"international_goals":1,"date_of_birth":"1998-11-05","height_cm":187,"team":{"kind":"team","team_id":22,"name":"Japan","fifa_code":"JPN"}}],"total":1248,"limit":50,"offset":550}